{
  "sensor_id": "SM_B5_BACH",
  "registros": [
    {
      "timestamp": "2025-09-30T11:09:48.337023",
      "ActivePower": 92271.40000000001,
      "TotalPowerFactor": 0.99,
      "RelativeTHDVoltage": 2.287,
      "Frequency": 60.0,
      "V1": 124.64,
      "V2": 124.44,
      "V3": 125.08,
      "I1": 240.0,
      "I2": 230.0,
      "I3": 280.0
    },
    {
      "timestamp": "2025-09-30T11:10:26.829815",
      "ActivePower": 94709.0,
      "TotalPowerFactor": 0.99,
      "RelativeTHDVoltage": 2.283,
      "Frequency": 59.96,
      "V1": 124.62,
      "V2": 124.29,
      "V3": 125.04,
      "I1": 250.0,
      "I2": 230.0,
      "I3": 290.0
    },
    {
      "timestamp": "2025-09-30T11:11:05.806833",
      "ActivePower": 94709.0,
      "TotalPowerFactor": 0.99,
      "RelativeTHDVoltage": 2.283,
      "Frequency": 59.96,
      "V1": 124.62,
      "V2": 124.29,
      "V3": 125.04,
      "I1": 250.0,
      "I2": 230.0,
      "I3": 290.0
    },
    {
      "timestamp": "2025-09-30T11:11:44.408860",
      "ActivePower": 94709.0,
      "TotalPowerFactor": 0.99,
      "RelativeTHDVoltage": 2.283,
      "Frequency": 59.96,
      "V1": 124.62,
      "V2": 124.29,
      "V3": 125.04,
      "I1": 250.0,
      "I2": 230.0,
      "I3": 290.0
    },
    {
      "timestamp": "2025-09-30T11:12:22.777529",
      "ActivePower": 94709.0,
      "TotalPowerFactor": 0.99,
      "RelativeTHDVoltage": 2.283,
      "Frequency": 59.96,
      "V1": 124.62,
      "V2": 124.29,
      "V3": 125.04,
      "I1": 250.0,
      "I2": 230.0,
      "I3": 290.0
    },
    {
      "timestamp": "2025-09-30T11:13:01.052312",
      "ActivePower": 92547.70000000001,
      "TotalPowerFactor": 0.99,
      "RelativeTHDVoltage": 2.259,
      "Frequency": 59.980000000000004,
      "V1": 124.62,
      "V2": 124.26,
      "V3": 124.99000000000001,
      "I1": 240.0,
      "I2": 230.0,
      "I3": 280.0
    },
    {
      "timestamp": "2025-09-30T11:13:39.338176",
      "ActivePower": 92547.70000000001,
      "TotalPowerFactor": 0.99,
      "RelativeTHDVoltage": 2.259,
      "Frequency": 59.980000000000004,
      "V1": 124.62,
      "V2": 124.26,
      "V3": 124.99000000000001,
      "I1": 240.0,
      "I2": 230.0,
      "I3": 280.0
    },
    {
      "timestamp": "2025-09-30T11:14:17.626371",
      "ActivePower": 92547.70000000001,
      "TotalPowerFactor": 0.99,
      "RelativeTHDVoltage": 2.259,
      "Frequency": 59.980000000000004,
      "V1": 124.62,
      "V2": 124.26,
      "V3": 124.99000000000001,
      "I1": 240.0,
      "I2": 230.0,
      "I3": 280.0
    },
    {
      "timestamp": "2025-09-30T11:14:56.004976",
      "ActivePower": 92547.70000000001,
      "TotalPowerFactor": 0.99,
      "RelativeTHDVoltage": 2.259,
      "Frequency": 59.980000000000004,
      "V1": 124.62,
      "V2": 124.26,
      "V3": 124.99000000000001,
      "I1": 240.0,
      "I2": 230.0,
      "I3": 280.0
    },
    {
      "timestamp": "2025-09-30T11:15:34.493478",
      "ActivePower": 97283.90000000001,
      "TotalPowerFactor": 0.99,
      "RelativeTHDVoltage": 2.206,
      "Frequency": 59.99,
      "V1": 124.54,
      "V2": 124.09,
      "V3": 125.03,
      "I1": 250.0,
      "I2": 260.0,
      "I3": 290.0
    },
    {
      "timestamp": "2025-09-30T11:16:12.743302",
      "ActivePower": 97283.90000000001,
      "TotalPowerFactor": 0.99,
      "RelativeTHDVoltage": 2.206,
      "Frequency": 59.99,
      "V1": 124.54,
      "V2": 124.09,
      "V3": 125.03,
      "I1": 250.0,
      "I2": 260.0,
      "I3": 290.0
    },
    {
      "timestamp": "2025-09-30T11:16:51.235752",
      "ActivePower": 97283.90000000001,
      "TotalPowerFactor": 0.99,
      "RelativeTHDVoltage": 2.206,
      "Frequency": 59.99,
      "V1": 124.54,
      "V2": 124.09,
      "V3": 125.03,
      "I1": 250.0,
      "I2": 260.0,
      "I3": 290.0
    },
    {
      "timestamp": "2025-09-30T11:17:29.917466",
      "ActivePower": 97283.90000000001,
      "TotalPowerFactor": 0.99,
      "RelativeTHDVoltage": 2.206,
      "Frequency": 59.99,
      "V1": 124.54,
      "V2": 124.09,
      "V3": 125.03,
      "I1": 250.0,
      "I2": 260.0,
      "I3": 290.0
    },
    {
      "timestamp": "2025-09-30T11:18:08.385025",
      "ActivePower": 105437.8,
      "TotalPowerFactor": 0.99,
      "RelativeTHDVoltage": 2.616,
      "Frequency": 59.980000000000004,
      "V1": 124.51,
      "V2": 124.11,
      "V3": 124.96000000000001,
      "I1": 250.0,
      "I2": 250.0,
      "I3": 280.0
    },
    {
      "timestamp": "2025-09-30T11:18:46.758083",
      "ActivePower": 105437.8,
      "TotalPowerFactor": 0.99,
      "RelativeTHDVoltage": 2.616,
      "Frequency": 59.980000000000004,
      "V1": 124.51,
      "V2": 124.11,
      "V3": 124.96000000000001,
      "I1": 250.0,
      "I2": 250.0,
      "I3": 280.0
    },
    {
      "timestamp": "2025-09-30T11:19:25.135741",
      "ActivePower": 105437.8,
      "TotalPowerFactor": 0.99,
      "RelativeTHDVoltage": 2.616,
      "Frequency": 59.980000000000004,
      "V1": 124.51,
      "V2": 124.11,
      "V3": 124.96000000000001,
      "I1": 250.0,
      "I2": 250.0,
      "I3": 280.0
    },
    {
      "timestamp": "2025-09-30T11:20:03.648606",
      "ActivePower": 95754.40000000001,
      "TotalPowerFactor": 0.99,
      "RelativeTHDVoltage": 2.305,
      "Frequency": 60.0,
      "V1": 124.54,
      "V2": 124.11,
      "V3": 124.9,
      "I1": 240.0,
      "I2": 250.0,
      "I3": 290.0
    },
    {
      "timestamp": "2025-09-30T11:20:41.953593",
      "ActivePower": 95754.40000000001,
      "TotalPowerFactor": 0.99,
      "RelativeTHDVoltage": 2.305,
      "Frequency": 60.0,
      "V1": 124.54,
      "V2": 124.11,
      "V3": 124.9,
      "I1": 240.0,
      "I2": 250.0,
      "I3": 290.0
    },
    {
      "timestamp": "2025-09-30T11:21:20.480240",
      "ActivePower": 95754.40000000001,
      "TotalPowerFactor": 0.99,
      "RelativeTHDVoltage": 2.305,
      "Frequency": 60.0,
      "V1": 124.54,
      "V2": 124.11,
      "V3": 124.9,
      "I1": 240.0,
      "I2": 250.0,
      "I3": 290.0
    },
    {
      "timestamp": "2025-09-30T11:21:58.735471",
      "ActivePower": 95754.40000000001,
      "TotalPowerFactor": 0.99,
      "RelativeTHDVoltage": 2.305,
      "Frequency": 60.0,
      "V1": 124.54,
      "V2": 124.11,
      "V3": 124.9,
      "I1": 240.0,
      "I2": 250.0,
      "I3": 290.0
    }
  ]
}